<?xml version="1.0"?>
<!DOCTYPE hibernate-mapping PUBLIC "-//Hibernate/Hibernate Mapping DTD 3.0//EN"
"http://www.hibernate.org/dtd/hibernate-mapping-3.0.dtd">
<!-- Generated 06/01/2015 21:06:20 by Hibernate Tools 4.3.1 -->
<hibernate-mapping>
    <class name="pojo.Login" table="login" catalog="controledegado" optimistic-lock="version">
        <id name="loginCodigo" type="java.lang.Integer">
            <column name="login_codigo" />
            <generator class="identity" />
        </id>
        <property name="loginNome" type="string">
            <column name="login_nome" length="35" not-null="true" />
        </property>
        <property name="loginSenha" type="string">
            <column name="login_senha" length="45" not-null="true" />
        </property>
    </class>
</hibernate-mapping>
